{"outerFolderName": "recordernew", "folderName": "1", "stepNumber": ["1", "2", "3", "4", "5", "6", "7"], "xpath": [["Open_Browser"], ["//input[@name=\"user-name\"]", "//input[@id=\"user-name\"]", "//input[@placeholder=\"Username\"]", "//input"], ["//input[@name=\"password\"]", "//input[@id=\"password\"]", "//input[@placeholder=\"Password\"]", "xpath=(//input)[2]", "(//input[contains(@class ,\"input_error form_input\")])[2]", "(//input[contains(@type ,\"password\")])[2]"], ["//input[@name=\"login-button\"]", "//input[@id=\"login-button\"]", "xpath=(//input)[3]", "(//input[contains(@class ,\"submit-button btn_action\")])[3]", "(//input[contains(@type ,\"submit\")])[3]"], ["//h4", "//h4,//h4[contains(., \"Accepted usernames are:\")]"], ["xpath=(//div)[3]", "(//div[contains(@class ,\"login_logo\")])[3]"], ["xpath=(//div)[11]", "(//div[contains(@class ,\"bot_column\")])[11]"]], "value": ["https://www.saucedemo.com/", "itrkrt", "djtjtrj", " ", " ", " ", " "], "property": ["", "", "", "", "", "", ""]}